{
	"AccStatus":{
		"TOKEN_REVOKE_TITLE":"出于安全考虑，您已退出。",
		"IDLE_TIME_DETECT_TITLE":"连线逾时提示",
		"IDLE_TIME_DETECT_DESC":"由于长时间未有操作，你的连线即将中断。如需继续，请按以下按钮。",
		"SESSION_TIMEOUT_TITLE":"连线逾时",
		"SESSION_TIMEOUT_DESC":"你已闲置了一段时间。基于保安理由，你的帐户已自动登出。如有需要，请再次登入。",
		"Account_Already_Activated_Title":"你曾经注册并已启动帐户。请直接登入积金易平台。",
		"Account_Not_Activated_Title":"你的帐户尚未启动。请先启动你的积金易帐户，再继续登入。",
		"Extra_Processing_Time_Title":"身分验证处理中",
		"Extra_Processing_Time_Desc":"我们需时验证你的身分，请耐心等待。验证完成后，我们将会以电邮通知你。",
		"RegistrationRequired_Title":"没有注册纪录",
		"RegistrationRequired_Desc":"没有与你提供的资料相符的积金易注册纪录。请先注册积金易，然后再启动帐户。",
		"OTP_Fail_Title":"无效的验证码，请再试一次。",
		"Account_Deactivated_Title":"你曾经停用你的积金易帐户。请立即重新启动你的帐户以继续。",
		"Account_Deregistered_Title":"你早前已从积金易撤销注册。如需透过积金易平台管理你的强积金，请重新注册。",
		"Account_Already_Registered_Title":"帐户已注册",
		"Account_Already_Registered_Desc":"你提供的雇主及公司获授权人资料的帐户已存在。请直接登入积金易平台。",
		"Extra_Processing_Time_Title_ER":"帐户启动审核中",
		"Extra_Processing_Time_Desc_ER":"我们需时审核你的帐户启动申请，请耐心等待。完成后，我们将会以电邮通知你。",
		"Pre_Login_Member_Enrolment_No_Record":"你的雇主尚未为你登记参加任何强积金计划。",
		"Login_Button":"登入",
		"Registration_Button":"立即注册",
		"Activation_Button":"立即启动",
		"OK_Button":"知道了",
		"Back_Home_Button":"返回主页",
		"Reactivated_Button":"立即重新启动",
		"Session_timeout_continue":"继续",
		"Reference_No":"参考编号："
	},
	"Yup_Verify":{
		"Invalid_bank_account_number":"无效的银行户口号码。",
		"lastNameRequired":"请提供英文或中文姓氏。",
		"bankSwiftCode":"无效的SWIFT代码格式。只允许{{min}} - {{max}}个大写字母及数字字符。",
		"EMAIL_ADDRESS":"无效的电邮地址。",
		"Max_Length":"最多{{max}}个字符",
		"Min_Length":"最少{{min}}个字符",
		"Required":"此栏必须输入。",
		"equalLength":"只允许{{length}}位数字",
		"emptyLength":"必需空白",
		"maxMobileNumber":"最多{{max}}位数字",
		"mobilePhoneNumber":"必须为有效的手机号码",
		"onlyEnglish":"只允许英文字符",
		"onlyEnglishAndNumber":"只允许英文和数字字符",
		"onlyNumber":"只允许数字字符",
		"onlyChines":"只允许中文字符",
		"minToDay":"不应该在今天之后",
		"minToDateOfEmployment":"不应该在受雇日期之前",
		"maxToDay":"日期不得迟于今天。",
		"registrationNo":"商业注册号码输入错误",
		"pleaseSelectArea":"请先选择地区",
		"pleaseSelectCountry":"请先选择国家",
		"maxNumber":"不能超过{{max}}位",
		"minNumber":"不能小于{{min}}位",
		"maxPercentage":"最大值不能超过{{max}}%",
		"minPercentage":"最小值不能小于{{min}}%",
		"maxCurrency":"不能超过{{max}}",
		"minCurrency":"不能小于{{min}}",
		"usernameFormat":"用户名称格式错误",
		"usernamneValid":"用户名无效",
		"passwordFormant":"密码格式错误",
		"passwordNotMatch":"密码不一致",
		"passwordNotSame":"新密码不能与当前密码一致",
		"Please_Verify":"请验证",
		"INPUT_IS_EMPTY_OR_INCORRECT":"输入空白或错误。",
		"eitherFlatFloorBlock":"必须输入单位/室，层数或座",
		"eitherBuildingStreet":"必须输入大厦或街道（街号及街道名称）",
		"fileTooLarge":"档案大小不可超过200M。",
		"memberGradeNameDuplicate":"组别名称不能一样",
		"payrollGroupNameDuplicate":"工资组别名称不能一样",
		"payrollGroupIdDuplicate":"工资组别编号不能一樣",
		"File_Number_Multi_Title":"档案数量超出限制",
		"File_Number_Multi_Desc":"每个上载框最多只能上载{{num}}个档案。请删除一些档案并重试。",
		"File_Number_Single_Title":"档案数量超出限制",
		"File_Number_Single_Desc":"只可上载1个档案。",
		"File_Type_Title":"无效的档案格式",
		"File_Type_Desc":"请上载正确的档案格式：{{acceptTypeDisplay}}",
		"File_Size_Title":"档案太大",
		"File_Size_Desc":"请选择{{size}}MB以内的档案。",
		"commencementDateMinDate":"Date of joining the scheme must be later than 2000/12/01",
		"commencementDateMaxDate":"Date of joining the scheme must be early than {{max}}",
		"maxToSpecificDay":"只允许日期是{{max}}或{{max}}之前",
		"noDefaultPayrollGroup":"cannot have no default payroll group",
		"noDefaultMemberGrade":"cannot have no default member grade",
		"Email_Unique":"电邮地址不能相同",
		"Phone_Unique":"手机号码不能相同",
		"Second_Phone_Unique":"电话号码不能相同",
		"hkidPassportNo":"无效的身分证明号码。",
		"ageFailed":"未能通过最低年龄要求",
		"Invalid_format":"无效的格式。",
		"ContributionBillsDate":"供款结单发出日必须早于或等于首次供款日。",
		"gradeNameDuplicate":"不接受重复的成员组别名称",
		"Invalid_Reason":"无效的原因",
		"Email_With_MPFA":"必须包含 @mpfa",
		"isBranchEqualBrNumber":"商业登记证的最后3个数字必须与分行编号相同。",
		"invalidPhoneNumber":"无效的电话号码",
		"minInvestmentAllocation":"基金分配百分比必须大于或等于{{min}}",
		"maxInvestmentAllocation":"基金分配百分比必须少于或等于{{max}}",
		"eitherCompanyName":"请提供公司的英文或中文名称。"
	},
	"header":{
		"HOME":"主页",
		"ENROL_AN_MPF_ACCOUNT":"登记强积金帐户",
		"MANAGE_YOUR_MPF":"管理强积金",
		"INVEST":"投资",
		"TRANSFER_YOUR_MPF":"转移强积金",
		"WITHDRAW_BENEFITS":"提取权益",
		"ER_MAKE_CONTRIBUTION":"管理供款",
		"MAKE_CONTRIBUTION":"供款",
		"CONTRIBUTION_RECORD":"供款纪录",
		"DEFAULT_CONTRIBUTION_RECORD":"拖欠供款纪录",
		"MAKE_NEW_CONTRIBUTION":"作出新供款",
		"MY_ACCOUNT":"我的帐户",
		"MY_RECORD":"我的纪录",
		"MY_LETTER_STATEMENT":"我的信件及报表",
		"PROFILE_MANAGEMENT":"帐户管理",
		"EMPF_ACCOUNT_SETTING":"积金易帐户设定",
		"EMPF_ACCOUNT_MGMT":"积金易帐户管理",
		"MPF_ACCOUNT_MGMT":"强积金帐户管理",
		"MORE_SERVICES":"更多服务",
		"LSP_SP_OFFSETTING":"抵销长期服务金/遣散费",
		"MY_STATEMENT":"我的报表",
		"ACTION_ITEMS":"Action Items",
		"NOTIFICATION":"Notification",
		"MANAGE_SCHEME":"管理计划",
		"ENROL_SCHEME":"登记计划",
		"MANAGE_ENROLLED_SCHEME":"管理已登记计划",
		"RESERVE_ACCOUNT_AND_FORFEITURE_ACCOUNT":"储备帐户及没收权益帐户",
		"MANAGE_EMPLOYEES":"管理雇员",
		"VIEW_EMPLOYEE_LIST":"查阅雇员列表",
		"ENROL_NEW_EMPLOYEES":"加入新雇员",
		"TRANSFER_FUNDS":"转移资金",
		"TERMINATE_EMPLOYEES":"终止雇员受雇",
		"VIEW_CONTRIBUTION_PERIOD":"查阅供款期",
		"VIEW_SUBMITTED_REMITTANCE_STATEMENTS":"查阅已提交的付款结算书",
		"VIEW_DEFAULT_CONTRIBUTION_AND_SURCHARGE_RECORD":"查阅拖欠供款及附加费纪录",
		"DESIGNATED_SAVING_ACCOUNT":"专项储蓄户口",
		"USER_MANAGEMENT":"用户管理",
		"MY_ACTION":"My Action",
		"enroll_scheme":"登记参加计划",
		"enrolled_scheme_management":"管理已参加的计划",
		"suspense_account_and_forfeiture_account":"暂存帐户及没收权益帐户",
		"manage_your_employee":"管理雇员",
		"employee_list":"雇员列表",
		"employee_enrollment":"雇员登记计划",
		"enroll_new_employee":"加入新雇员",
		"terminate employee":"终止雇员受雇",
		"transfer":"转移你的强积金",
		"contribution_record":"供款纪录",
		"submission_record":"提交纪录",
		"default_contribution_record":"拖欠供款纪录",
		"my_record":"我的纪录",
		"statement":"我的报表",
		"designated_saving_account":"专项储蓄户口",
		"profile_management":"帐户管理",
		"user_management":"用户管理",
		"eMPF_account_setting":"积金易帐户设定",
		"scheme_management":"管理计划",
		"home":"主页",
		"contribution":"管理供款",
		"terminate_employee":"终止雇员受雇",
		"my_account":"我的帐户",
		"log_out":"登出"
	},
	"figure":{
		"1":"一",
		"2":"二",
		"3":"三",
		"4":"四",
		"5":"五",
		"6":"六",
		"7":"七",
		"8":"八",
		"9":"九"
	},
	"Add_Intermediary":"新增中介人",
	"I_M_NOT_A_ROBOT":"我不是机器人",
	"InvalidLoginVal":"用户名称或密码输入错误",
	"Login_eMPF_Acc":"登入积金易",
	"Login":"登入",
	"Auto_Logout":"身分验证失败",
	"Auto_Logout_Desc":"我们未能验证你的身分。基于保安理由，你已被自动登出。",
	"Log_In_Again":"重新登入",
	"Retrieve_Enrolment":"查找储存纪录以继续",
	"Enrolment_Submitted":"已提交僱員登記參加計劃申請",
	"Enrolment_Submitted_Desc":"你的帐户登记申请已提交，当登记完成后，我们会通知你有关结果。",
	"Setup_Account":"建立用户名称及密码",
	"Account_Setup":"建立用户名称及密码",
	"Select_OTP_Method":"选取并输入已登记的联络资料，以收取一次性密码。",
	"Methed_to":"{{type}} to {{value}}",
	"Retrieve_Record":"查找储存纪录以继续",
	"Home":"主页",
	"Scheme":"管理已登记计划",
	"Manage_Employee":"管理雇员",
	"Contribution":"供款",
	"Other_Services":"我的帐户",
	"eMPF_Account_Reg_Title":"註冊你的積金易帳戶",
	"eMPF_Account_Reg_Desc":"只需幾步，即可建立你的積金易帳戶。請選擇你的角色。",
	"Employer_Registration":"僱主註冊",
	"Er_Reg_Desc":"只需3步，即可建立你的積金易帳戶",
	"Er_Reg_Step1_Title":"第1步 輸入公司資料",
	"Er_Reg_Step1_Desc":"提供公司資料、地址，及選擇偏好通訊語言。",
	"Er_Reg_Step2_Title":"第2步 設定公司獲授權人及聯絡人",
	"Er_Reg_Step2_Desc":"設定公司獲授權人及聯絡人，並提供所需個人資料。",
	"Er_Reg_Step3_Title":"第3步 上載證明文件",
	"Er_Reg_Step3_Desc":"上載公司相關證明文件，如商業登記證。",
	"Required_Item":"所需項目",
	"Required_Item_Note":"在開始前，請先準備以下項目，以便順利進行註冊:",
	"Required_Item_Desc1":"商業登記／合夥契約／非法人團體的證明",
	"Required_Item_Desc2":"公司相關的證明文件",
	"Required_Item_Desc3":"手機（用以接收一次性密碼作驗證及透過流動應用程式啟動帳戶，如適用）",
	"Start_Registration":"開始註冊",
	"Verify":"验证",
	"SelectOption":"",
	"Member":"成员",
	"Employer":"雇主",
	"Login_ID_Type":"登入帐户类型",
	"ID_Type":"身分证明类别",
	"Username":"用户名称",
	"Password":"密码",
	"Forgot":"忘记{{value}}",
	"eMPF_ID":"积金易号码",
	"Login_iAM_Smart":"智方便登入",
	"iAM_Smart_Popover":"表示该项由「智方便」提供。",
	"OR":"或",
	"Remeber_Me":"记住我",
	"No_Account":"未有帐户？",
	"Register":"注册",
	"Create":"确定",
	"Account_Activation":"启动你的帐户",
	"Activation_Desc":"基於保安理由，請先選擇其中一種方式以驗證你的身分。",
	"Select_Activation":"选择身分验证方式",
	"Select_Activation_desc":"基于保安理由，请先选择其中一种方式以验证你的身分。",
	"Activate_Your_Account":"启动帐户",
	"Activate_Your_Account_Desc":"请输入以下资料，以启动帐户。",
	"HKID_desc":"香港身份证号码（如身份证号码为A123456(B)，请输入A123456B）",
	"Activate_Your_Account_set":"請先啟動你的積金易帳戶，再繼續登入。",
	"Activate_Accont_Desc":"你的积金易号码是一组供你终身访问积金易平台的独特号码。由现在起，你可在积金易平台上管理你名下的所有强积金帐户。",
	"Activate_Now_Desc":"你已成功注册积金易帐户，请立即启动帐户。",
	"Activate_Now":"立即启动",
	"Passoword_Updated_desc":"你的密碼已成功更新。",
	"Account_Locked":"帐户已锁定",
	"Account_Locked_desc":"基于保安理由，你的帐户已被锁定。请重设密码。",
	"Send_2FA":"发送一次性密码",
	"ID_Passport":"香港身份證號碼/護照號碼",
	"Reset_Password":"重设密码",
	"Confirm_Password":"确认密码",
	"Cancel":"取消",
	"OK":"知道了",
	"verification_code":"输入验证码",
	"verification_instruction":"请输入我们以{{method}}发送到<target>{{target}}</target>的验证码。",
	"Confirm":"确定",
	"Confirm_reg":"确认",
	"2FA":"双重认证",
	"2FA_Describe":"输入香港身份证号码及一次性密码验证",
	"2FA_Describe_HKID":"输入香港身份证号码及一次性密码验证",
	"Select_Identity":"选择身分验证方式",
	"Identity_Describe":"基于保安理由，请先选择其中一种方式以验证你的身分。",
	"eKYC":"电子身分验证",
	"eKYC_Describe":"掃描身分證及進行人臉識別時，請注意以下事項。",
	"iAM_Smart":"「智方便」",
	"iAM_Smart_Describe":"登入「智方便」验证"
}